add_colorprint/LICENSE
add_colorprint/README.MD
add_colorprint/__init__.py
add_colorprint/requirements.txt
add_colorprint/thirdparty.json
add_colorprint-0.10.dist-info/LICENSE.rst
add_colorprint-0.10.dist-info/METADATA
add_colorprint-0.10.dist-info/WHEEL
add_colorprint-0.10.dist-info/top_level.txt
add_colorprint-0.10.dist-info/RECORD
